dbt/adapters/cockroachdb/__init__.py
dbt/adapters/cockroachdb/__version__.py
dbt/adapters/cockroachdb/connections.py
dbt/adapters/cockroachdb/impl.py
dbt/include/cockroachdb/__init__.py
dbt/include/cockroachdb/dbt_project.yml
dbt/include/cockroachdb/profile_template.yml
dbt/include/cockroachdb/macros/adapters.sql
dbt/include/cockroachdb/macros/catalog.sql
dbt/include/cockroachdb/macros/adapters/columns.sql
dbt/include/cockroachdb/macros/adapters/freshness.sql
dbt/include/cockroachdb/macros/adapters/metadata.sql
dbt_cockroachdb-1.1.2.dist-info/LICENSE
dbt_cockroachdb-1.1.2.dist-info/METADATA
dbt_cockroachdb-1.1.2.dist-info/WHEEL
dbt_cockroachdb-1.1.2.dist-info/top_level.txt
dbt_cockroachdb-1.1.2.dist-info/RECORD
