Metadata-Version: 2.1
Name: dbt-cockroachdb
Version: 1.1.2
Summary: The cockroachdb adapter plugin for dbt (data build tool)
Home-page: https://github.com/salaluf
Author: Shoham Alaluf
Author-email: author@gmail.com
License: UNKNOWN
Platform: UNKNOWN
Classifier: Development Status :: 5 - Production/Stable
Classifier: License :: OSI Approved :: Apache Software License
Classifier: Operating System :: Microsoft :: Windows
Classifier: Operating System :: MacOS :: MacOS X
Classifier: Operating System :: POSIX :: Linux
Classifier: Programming Language :: Python :: 3.7
Classifier: Programming Language :: Python :: 3.8
Classifier: Programming Language :: Python :: 3.9
Classifier: Programming Language :: Python :: 3.10
Classifier: Programming Language :: Python :: 3.11
Requires-Python: >=3.7
License-File: LICENSE
Requires-Dist: dbt-core (==1.1.2)
Requires-Dist: psycopg-binary (~=3.1)
